dpy_paginator.py
dpy_paginator-1.1.1.dist-info/LICENSE
dpy_paginator-1.1.1.dist-info/METADATA
dpy_paginator-1.1.1.dist-info/WHEEL
dpy_paginator-1.1.1.dist-info/RECORD
