Metadata-Version: 2.1
Name: dpy-paginator
Version: 1.1.1
Summary: A paginator utility for discord.py with no additional dependencies that makes paginating embeds easier.
Home-page: https://github.com/OnceYT/dpy-paginator
License: MIT
Author: OnceYT
Author-email: sahaa6919@gmail.com
Requires-Python: >=3.9,<4.0
Classifier: License :: OSI Approved :: MIT License
Classifier: Programming Language :: Python :: 3
Classifier: Programming Language :: Python :: 3.9
Classifier: Programming Language :: Python :: 3.10
Classifier: Programming Language :: Python :: 3.11
Requires-Dist: discord.py (>=2.0.0,<3.0.0)
